.installed.cfg
.long-description.html
MANIFEST.in
README.rst
access.log
bluebream.ini
bluebream.zcml
bootstrap.py
buildout.cfg
setup.py
z3.log
zope.conf
collective/__init__.py
collective/__init__.pyc
collective.recipe.bluebream.egg-info/PKG-INFO
collective.recipe.bluebream.egg-info/SOURCES.txt
collective.recipe.bluebream.egg-info/dependency_links.txt
collective.recipe.bluebream.egg-info/entry_points.txt
collective.recipe.bluebream.egg-info/namespace_packages.txt
collective.recipe.bluebream.egg-info/requires.txt
collective.recipe.bluebream.egg-info/top_level.txt
collective/recipe/__init__.py
collective/recipe/__init__.pyc
collective/recipe/bluebream/__init__.py
collective/recipe/bluebream/__init__.pyc
collective/recipe/bluebream/configure.zcml
collective/recipe/bluebream/overrides.zcml
collective/recipe/bluebream/package-includes.zcml
collective/recipe/bluebream/securitypolicy.zcml
collective/recipe/bluebream/welcome/__init__.py
collective/recipe/bluebream/welcome/__init__.pyc
collective/recipe/bluebream/welcome/app.py
collective/recipe/bluebream/welcome/app.pyc
collective/recipe/bluebream/welcome/configure.zcml
collective/recipe/bluebream/welcome/ftests.txt
collective/recipe/bluebream/welcome/index.pt
collective/recipe/bluebream/welcome/interfaces.py
collective/recipe/bluebream/welcome/interfaces.pyc
collective/recipe/bluebream/welcome/views.py
collective/recipe/bluebream/welcome/views.pyc
collective/recipe/bluebream/welcome/static/logo.png
collective/recipe/bluebream/welcome/static/style.css
docs/HISTORY.txt
src/my.package/setup.py
src/my.package/my.package.egg-info/PKG-INFO
src/my.package/my.package.egg-info/SOURCES.txt
src/my.package/my.package.egg-info/dependency_links.txt
src/my.package/my.package.egg-info/top_level.txt