Metadata-Version: 1.0
Name: collective.recipe.bluebream
Version: 0.4.0
Summary: collective.recipe.bluebream is a zc.buildout recipe         you can use to bootstrap a Bluebream project
Home-page: https://github.com/collective/collective.recipe.bluebream
Author: Alex Clark
Author-email: aclark@aclark.net
License: ZPL
Platform: UNKNOWN
